ordersystem/__init__.py
ordersystem/custom_exceptions.py
ordersystem/meals.py
ordersystem/menu.py
ordersystem/order_system.py
tests/__init__.py
tests/order_tests.py
ordersystem-1.1.dist-info/LICENSE
ordersystem-1.1.dist-info/METADATA
ordersystem-1.1.dist-info/WHEEL
ordersystem-1.1.dist-info/top_level.txt
ordersystem-1.1.dist-info/RECORD
