Metadata-Version: 2.1
Name: ordersystem
Version: 1.1
Summary: OrderSystem to take customer orders
Home-page: https://github.com/SUzoegwu/OrderSystem
Author: Somtochukwu Uzoegwu
License: MIT
Keywords: order system ordersystem order_system
Platform: UNKNOWN
Classifier: Programming Language :: Python :: 3
Classifier: License :: OSI Approved :: MIT License
Classifier: Development Status :: 4 - Beta
Classifier: Intended Audience :: Developers
Classifier: Operating System :: OS Independent
Requires-Python: >=3.8
License-File: LICENSE
